{"file:///f%3A/SocialApp/vite.config.js":{"language":"JavaScript","code":18,"comment":1,"blank":2},"file:///f%3A/SocialApp/src/utils/parseText.jsx":{"language":"JavaScript JSX","code":11,"comment":0,"blank":3},"file:///f%3A/SocialApp/src/utils/helpers.js":{"language":"JavaScript","code":39,"comment":0,"blank":7},"file:///f%3A/SocialApp/src/context/ThemeContext.jsx":{"language":"JavaScript JSX","code":21,"comment":0,"blank":7},"file:///f%3A/SocialApp/src/context/SearchContext.jsx":{"language":"JavaScript JSX","code":17,"comment":0,"blank":6},"file:///f%3A/SocialApp/src/utils/contstants.js":{"language":"JavaScript","code":0,"comment":0,"blank":1},"file:///f%3A/SocialApp/src/context/ScreenSizeContext.jsx":{"language":"JavaScript JSX","code":18,"comment":0,"blank":5},"file:///f%3A/SocialApp/src/context/AuthContext.js":{"language":"JavaScript","code":0,"comment":0,"blank":1},"file:///f%3A/SocialApp/src/App.jsx":{"language":"JavaScript JSX","code":100,"comment":1,"blank":8},"file:///f%3A/SocialApp/public/icon.svg":{"language":"XML","code":18,"comment":0,"blank":4},"file:///f%3A/SocialApp/package.json":{"language":"JSON","code":39,"comment":0,"blank":1},"file:///f%3A/SocialApp/README.md":{"language":"Markdown","code":61,"comment":0,"blank":20},"file:///f%3A/SocialApp/src/ui/FormTail.jsx":{"language":"JavaScript JSX","code":40,"comment":0,"blank":7},"file:///f%3A/SocialApp/src/ui/FormHeader.jsx":{"language":"JavaScript JSX","code":52,"comment":0,"blank":7},"file:///f%3A/SocialApp/src/ui/FormRow.jsx":{"language":"JavaScript JSX","code":0,"comment":0,"blank":1},"file:///f%3A/SocialApp/src/ui/Form.jsx":{"language":"JavaScript JSX","code":28,"comment":0,"blank":3},"file:///f%3A/SocialApp/src/ui/FakeAvatar.jsx":{"language":"JavaScript JSX","code":21,"comment":0,"blank":4},"file:///f%3A/SocialApp/src/ui/ErrorFallBack.jsx":{"language":"JavaScript JSX","code":52,"comment":0,"blank":8},"file:///f%3A/SocialApp/src/ui/ErrorBoundary.jsx":{"language":"JavaScript JSX","code":18,"comment":0,"blank":5},"file:///f%3A/SocialApp/src/ui/DeletePopup.jsx":{"language":"JavaScript JSX","code":50,"comment":0,"blank":8},"file:///f%3A/SocialApp/src/ui/ButtonIcon.jsx":{"language":"JavaScript JSX","code":53,"comment":0,"blank":6},"file:///f%3A/SocialApp/src/ui/Badge.jsx":{"language":"JavaScript JSX","code":31,"comment":0,"blank":5},"file:///f%3A/SocialApp/src/ui/Button.jsx":{"language":"JavaScript JSX","code":100,"comment":0,"blank":6},"file:///f%3A/SocialApp/src/ui/Avatar.jsx":{"language":"JavaScript JSX","code":30,"comment":0,"blank":7},"file:///f%3A/SocialApp/src/ui/AppLayout.jsx":{"language":"JavaScript JSX","code":82,"comment":0,"blank":12},"file:///f%3A/SocialApp/src/ui/Modal.jsx":{"language":"JavaScript JSX","code":119,"comment":0,"blank":11},"file:///f%3A/SocialApp/src/ui/MiniSpinner.jsx":{"language":"JavaScript JSX","code":5,"comment":0,"blank":3},"file:///f%3A/SocialApp/src/ui/MenuItem.jsx":{"language":"JavaScript JSX","code":27,"comment":0,"blank":4},"file:///f%3A/SocialApp/src/ui/Menu.jsx":{"language":"JavaScript JSX","code":33,"comment":0,"blank":4},"file:///f%3A/SocialApp/src/ui/Logo.jsx":{"language":"JavaScript JSX","code":31,"comment":0,"blank":4},"file:///f%3A/SocialApp/src/ui/ListItem.jsx":{"language":"JavaScript JSX","code":10,"comment":0,"blank":3},"file:///f%3A/SocialApp/src/ui/Label.jsx":{"language":"JavaScript JSX","code":29,"comment":0,"blank":3},"file:///f%3A/SocialApp/src/ui/Input.jsx":{"language":"JavaScript JSX","code":28,"comment":0,"blank":3},"file:///f%3A/SocialApp/src/ui/Header.jsx":{"language":"JavaScript JSX","code":105,"comment":1,"blank":13},"file:///f%3A/SocialApp/src/ui/ProtectedRoutes.jsx":{"language":"JavaScript JSX","code":19,"comment":0,"blank":6},"file:///f%3A/SocialApp/src/ui/PostModal.jsx":{"language":"JavaScript JSX","code":168,"comment":0,"blank":19},"file:///f%3A/SocialApp/src/ui/OnlineSign.jsx":{"language":"JavaScript JSX","code":15,"comment":0,"blank":2},"file:///f%3A/SocialApp/src/ui/NotificationCount.jsx":{"language":"JavaScript JSX","code":14,"comment":0,"blank":4},"file:///f%3A/SocialApp/src/ui/ScrollBtn.jsx":{"language":"JavaScript JSX","code":24,"comment":0,"blank":2},"file:///f%3A/SocialApp/src/ui/NavItem.jsx":{"language":"JavaScript JSX","code":0,"comment":0,"blank":1},"file:///f%3A/SocialApp/src/ui/Row.jsx":{"language":"JavaScript JSX","code":11,"comment":0,"blank":3},"file:///f%3A/SocialApp/src/ui/SearchInput.jsx":{"language":"JavaScript JSX","code":52,"comment":1,"blank":9},"file:///f%3A/SocialApp/src/ui/Sidebar.jsx":{"language":"JavaScript JSX","code":75,"comment":0,"blank":6},"file:///f%3A/SocialApp/src/styles/index.css":{"language":"PostCSS","code":8,"comment":0,"blank":2},"file:///f%3A/SocialApp/src/styles/GolobalStyles.js":{"language":"JavaScript","code":203,"comment":0,"blank":3},"file:///f%3A/SocialApp/src/ui/UserSidebarInfo.jsx":{"language":"JavaScript JSX","code":39,"comment":0,"blank":5},"file:///f%3A/SocialApp/src/ui/ThemeToggle.jsx":{"language":"JavaScript JSX","code":44,"comment":0,"blank":5},"file:///f%3A/SocialApp/src/ui/Spinner.jsx":{"language":"JavaScript JSX","code":24,"comment":0,"blank":4},"file:///f%3A/SocialApp/index.html":{"language":"HTML","code":17,"comment":0,"blank":2},"file:///f%3A/SocialApp/src/services/supabase.js":{"language":"JavaScript","code":9,"comment":1,"blank":4},"file:///f%3A/SocialApp/src/services/apiMessages.js":{"language":"JavaScript","code":169,"comment":22,"blank":37},"file:///f%3A/SocialApp/src/services/apiLikes.js":{"language":"JavaScript","code":80,"comment":7,"blank":16},"file:///f%3A/SocialApp/src/services/apiComments.js":{"language":"JavaScript","code":115,"comment":5,"blank":19},"file:///f%3A/SocialApp/src/services/apiAuth.js":{"language":"JavaScript","code":71,"comment":2,"blank":23},"file:///f%3A/SocialApp/src/services/apiUsers.js":{"language":"JavaScript","code":163,"comment":6,"blank":39},"file:///f%3A/SocialApp/src/services/apiStories.js":{"language":"JavaScript","code":230,"comment":22,"blank":52},"file:///f%3A/SocialApp/src/services/apiStorage.js":{"language":"JavaScript","code":62,"comment":24,"blank":31},"file:///f%3A/SocialApp/src/services/apiReposts.js":{"language":"JavaScript","code":64,"comment":4,"blank":14},"file:///f%3A/SocialApp/src/services/apiPresence.js":{"language":"JavaScript","code":47,"comment":4,"blank":11},"file:///f%3A/SocialApp/src/services/apiPosts.js":{"language":"JavaScript","code":226,"comment":8,"blank":35},"file:///f%3A/SocialApp/src/services/apiNotifications.js":{"language":"JavaScript","code":92,"comment":6,"blank":21},"file:///f%3A/SocialApp/src/main.jsx":{"language":"JavaScript JSX","code":10,"comment":0,"blank":2},"file:///f%3A/SocialApp/src/pages/Signup.jsx":{"language":"JavaScript JSX","code":5,"comment":0,"blank":3},"file:///f%3A/SocialApp/src/pages/Profile.jsx":{"language":"JavaScript JSX","code":22,"comment":0,"blank":4},"file:///f%3A/SocialApp/src/pages/Notifications.jsx":{"language":"JavaScript JSX","code":13,"comment":0,"blank":4},"file:///f%3A/SocialApp/src/pages/NotFound.jsx":{"language":"JavaScript JSX","code":4,"comment":0,"blank":2},"file:///f%3A/SocialApp/src/pages/Messages.jsx":{"language":"JavaScript JSX","code":5,"comment":0,"blank":3},"file:///f%3A/SocialApp/src/pages/PostDetails.jsx":{"language":"JavaScript JSX","code":142,"comment":2,"blank":17},"file:///f%3A/SocialApp/src/pages/Login.jsx":{"language":"JavaScript JSX","code":5,"comment":0,"blank":3},"file:///f%3A/SocialApp/src/pages/Home.jsx":{"language":"JavaScript JSX","code":21,"comment":0,"blank":4},"file:///f%3A/SocialApp/src/pages/Discover.jsx":{"language":"JavaScript JSX","code":17,"comment":0,"blank":4},"file:///f%3A/SocialApp/src/pages/CheckEmail.jsx":{"language":"JavaScript JSX","code":38,"comment":0,"blank":7},"file:///f%3A/SocialApp/src/hooks/useScreenSize.js":{"language":"JavaScript","code":33,"comment":0,"blank":8},"file:///f%3A/SocialApp/src/hooks/useOutsideClick.js":{"language":"JavaScript","code":16,"comment":0,"blank":5},"file:///f%3A/SocialApp/src/hooks/useMoveBack.js":{"language":"JavaScript","code":5,"comment":0,"blank":2},"file:///f%3A/SocialApp/src/hooks/useLocalStorageState.js":{"language":"JavaScript","code":18,"comment":0,"blank":4},"file:///f%3A/SocialApp/src/hooks/useGetPage.js":{"language":"JavaScript","code":15,"comment":0,"blank":5},"file:///f%3A/SocialApp/src/hooks/useDebounce.js":{"language":"JavaScript","code":11,"comment":0,"blank":5},"file:///f%3A/SocialApp/src/features/authentication/useUser.js":{"language":"JavaScript","code":10,"comment":0,"blank":3},"file:///f%3A/SocialApp/src/features/authentication/useSignup.js":{"language":"JavaScript","code":21,"comment":0,"blank":4},"file:///f%3A/SocialApp/src/features/authentication/useLogout.js":{"language":"JavaScript","code":20,"comment":1,"blank":4},"file:///f%3A/SocialApp/src/features/authentication/SignupForm.jsx":{"language":"JavaScript JSX","code":161,"comment":0,"blank":13},"file:///f%3A/SocialApp/src/features/authentication/useLogin.js":{"language":"JavaScript","code":21,"comment":0,"blank":4},"file:///f%3A/SocialApp/src/features/authentication/LoginForm.jsx":{"language":"JavaScript JSX","code":133,"comment":0,"blank":14},"file:///f%3A/SocialApp/src/features/messaging/MessagesList.jsx":{"language":"JavaScript JSX","code":73,"comment":0,"blank":10},"file:///f%3A/SocialApp/src/features/messaging/MessageInput.jsx":{"language":"JavaScript JSX","code":62,"comment":0,"blank":8},"file:///f%3A/SocialApp/src/features/messaging/MessagesLayout.jsx":{"language":"JavaScript JSX","code":51,"comment":0,"blank":7},"file:///f%3A/SocialApp/src/features/messaging/MessageBubble.jsx":{"language":"JavaScript JSX","code":118,"comment":0,"blank":11},"file:///f%3A/SocialApp/src/features/messaging/ConversationsList.jsx":{"language":"JavaScript JSX","code":75,"comment":0,"blank":7},"file:///f%3A/SocialApp/src/features/messaging/ConversationItem.jsx":{"language":"JavaScript JSX","code":77,"comment":0,"blank":11},"file:///f%3A/SocialApp/src/features/messaging/ChatWindow.jsx":{"language":"JavaScript JSX","code":47,"comment":0,"blank":8},"file:///f%3A/SocialApp/src/features/messaging/useUnreadCount.js":{"language":"JavaScript","code":15,"comment":0,"blank":4},"file:///f%3A/SocialApp/src/features/messaging/useRealtimeMessages.js":{"language":"JavaScript","code":29,"comment":1,"blank":5},"file:///f%3A/SocialApp/src/features/messaging/useSendMessage.js":{"language":"JavaScript","code":21,"comment":0,"blank":3},"file:///f%3A/SocialApp/src/features/messaging/ChatHeader.jsx":{"language":"JavaScript JSX","code":109,"comment":0,"blank":10},"file:///f%3A/SocialApp/src/features/messaging/useMessages.js":{"language":"JavaScript","code":15,"comment":0,"blank":3},"file:///f%3A/SocialApp/src/features/messaging/useDeleteMessage.js":{"language":"JavaScript","code":20,"comment":0,"blank":3},"file:///f%3A/SocialApp/src/features/messaging/useMarkConversationAsRead.js":{"language":"JavaScript","code":20,"comment":0,"blank":4},"file:///f%3A/SocialApp/src/features/messaging/useDeleteConversation.js":{"language":"JavaScript","code":22,"comment":0,"blank":4},"file:///f%3A/SocialApp/src/features/messaging/useConversations.js":{"language":"JavaScript","code":13,"comment":0,"blank":3},"file:///f%3A/SocialApp/src/features/stories/Storybar.jsx":{"language":"JavaScript JSX","code":40,"comment":0,"blank":6},"file:///f%3A/SocialApp/src/features/stories/StoriesList.jsx":{"language":"JavaScript JSX","code":46,"comment":0,"blank":6},"file:///f%3A/SocialApp/src/features/stories/CreateStoryModal.jsx":{"language":"JavaScript JSX","code":59,"comment":0,"blank":6},"file:///f%3A/SocialApp/src/features/stories/CreateStory.jsx":{"language":"JavaScript JSX","code":86,"comment":0,"blank":3},"file:///f%3A/SocialApp/src/features/stories/ViewsModal.jsx":{"language":"JavaScript JSX","code":147,"comment":0,"blank":16},"file:///f%3A/SocialApp/src/features/stories/useUserStories.js":{"language":"JavaScript","code":14,"comment":0,"blank":3},"file:///f%3A/SocialApp/src/features/stories/useViewStory.js":{"language":"JavaScript","code":13,"comment":0,"blank":4},"file:///f%3A/SocialApp/src/features/stories/useStoryViewers.js":{"language":"JavaScript","code":14,"comment":0,"blank":3},"file:///f%3A/SocialApp/src/features/stories/useUnviewedStoriesCount.js":{"language":"JavaScript","code":9,"comment":0,"blank":3},"file:///f%3A/SocialApp/src/features/stories/useStories.js":{"language":"JavaScript","code":13,"comment":0,"blank":3},"file:///f%3A/SocialApp/src/features/stories/useDeleteStory.js":{"language":"JavaScript","code":22,"comment":3,"blank":6},"file:///f%3A/SocialApp/src/features/stories/useRealtimeStories.js":{"language":"JavaScript","code":19,"comment":0,"blank":4},"file:///f%3A/SocialApp/src/features/stories/useCreateStory.js":{"language":"JavaScript","code":21,"comment":0,"blank":3},"file:///f%3A/SocialApp/src/features/stories/StoryViewer.jsx":{"language":"JavaScript JSX","code":293,"comment":6,"blank":35},"file:///f%3A/SocialApp/src/features/stories/StoryCircle.jsx":{"language":"JavaScript JSX","code":58,"comment":0,"blank":2},"file:///f%3A/SocialApp/src/features/discover/useSuggestedUsers.js":{"language":"JavaScript","code":13,"comment":0,"blank":2},"file:///f%3A/SocialApp/src/features/discover/useUserProfile.js":{"language":"JavaScript","code":10,"comment":0,"blank":3},"file:///f%3A/SocialApp/src/features/discover/useSearchUsers.js":{"language":"JavaScript","code":10,"comment":0,"blank":3},"file:///f%3A/SocialApp/src/features/discover/useFollow.js":{"language":"JavaScript","code":41,"comment":0,"blank":8},"file:///f%3A/SocialApp/src/features/discover/Suggestions.jsx":{"language":"JavaScript JSX","code":41,"comment":0,"blank":9},"file:///f%3A/SocialApp/src/features/discover/DiscoverUserCard.jsx":{"language":"JavaScript JSX","code":31,"comment":0,"blank":4},"file:///f%3A/SocialApp/src/features/discover/FollowButton.jsx":{"language":"JavaScript JSX","code":0,"comment":0,"blank":1},"file:///f%3A/SocialApp/src/features/discover/DiscoverCardTail.jsx":{"language":"JavaScript JSX","code":62,"comment":0,"blank":6},"file:///f%3A/SocialApp/src/features/discover/DiscoverCardHeader.jsx":{"language":"JavaScript JSX","code":86,"comment":0,"blank":1},"file:///f%3A/SocialApp/src/features/discover/DiscoverCardBody.jsx":{"language":"JavaScript JSX","code":74,"comment":0,"blank":11},"file:///f%3A/SocialApp/src/features/profile/useFollowersCount.js":{"language":"JavaScript","code":12,"comment":0,"blank":3},"file:///f%3A/SocialApp/src/features/profile/ProfileImages.jsx":{"language":"JavaScript JSX","code":163,"comment":3,"blank":22},"file:///f%3A/SocialApp/src/features/profile/UpdateUserModal.jsx":{"language":"JavaScript JSX","code":198,"comment":0,"blank":18},"file:///f%3A/SocialApp/src/features/profile/ProfileHeader.jsx":{"language":"JavaScript JSX","code":15,"comment":1,"blank":4},"file:///f%3A/SocialApp/src/features/profile/FollowingsModal.jsx":{"language":"JavaScript JSX","code":68,"comment":1,"blank":10},"file:///f%3A/SocialApp/src/features/profile/FollowingItem.jsx":{"language":"JavaScript JSX","code":56,"comment":0,"blank":6},"file:///f%3A/SocialApp/src/features/profile/FollowersModal.jsx":{"language":"JavaScript JSX","code":67,"comment":0,"blank":9},"file:///f%3A/SocialApp/src/features/profile/FollowerItem.jsx":{"language":"JavaScript JSX","code":56,"comment":0,"blank":6},"file:///f%3A/SocialApp/src/features/profile/FollowButtonProfile.jsx":{"language":"JavaScript JSX","code":20,"comment":0,"blank":3},"file:///f%3A/SocialApp/src/features/profile/useUploadCover.js":{"language":"JavaScript","code":17,"comment":0,"blank":3},"file:///f%3A/SocialApp/src/features/profile/useUserPosts.js":{"language":"JavaScript","code":29,"comment":0,"blank":4},"file:///f%3A/SocialApp/src/features/profile/useUploadAvatar.js":{"language":"JavaScript","code":17,"comment":0,"blank":4},"file:///f%3A/SocialApp/src/features/profile/useUpdateUserDetails.js":{"language":"JavaScript","code":22,"comment":0,"blank":3},"file:///f%3A/SocialApp/src/features/profile/UserPosts.jsx":{"language":"JavaScript JSX","code":73,"comment":0,"blank":12},"file:///f%3A/SocialApp/src/features/profile/UserDetailsCard.jsx":{"language":"JavaScript JSX","code":256,"comment":0,"blank":25},"file:///f%3A/SocialApp/src/features/profile/useFollowingsUsers.js":{"language":"JavaScript","code":15,"comment":0,"blank":2},"file:///f%3A/SocialApp/src/features/profile/useFollowingsCount.js":{"language":"JavaScript","code":11,"comment":0,"blank":3},"file:///f%3A/SocialApp/src/features/profile/useIsFollowing.js":{"language":"JavaScript","code":10,"comment":0,"blank":3},"file:///f%3A/SocialApp/src/features/profile/useFollowersUsers.js":{"language":"JavaScript","code":15,"comment":0,"blank":2},"file:///f%3A/SocialApp/src/features/posts/PostCardActions.jsx":{"language":"JavaScript JSX","code":92,"comment":0,"blank":11},"file:///f%3A/SocialApp/src/features/posts/PostCard.jsx":{"language":"JavaScript JSX","code":92,"comment":2,"blank":10},"file:///f%3A/SocialApp/src/features/posts/ImageUploader.jsx":{"language":"JavaScript JSX","code":177,"comment":3,"blank":26},"file:///f%3A/SocialApp/src/features/posts/Hashtag.jsx":{"language":"JavaScript JSX","code":10,"comment":0,"blank":3},"file:///f%3A/SocialApp/src/features/posts/CreatePost.jsx":{"language":"JavaScript JSX","code":73,"comment":0,"blank":10},"file:///f%3A/SocialApp/src/features/posts/CreateComment.jsx":{"language":"JavaScript JSX","code":67,"comment":0,"blank":8},"file:///f%3A/SocialApp/src/features/posts/CommentsBox.jsx":{"language":"JavaScript JSX","code":73,"comment":2,"blank":8},"file:///f%3A/SocialApp/src/features/posts/CommentItem.jsx":{"language":"JavaScript JSX","code":169,"comment":1,"blank":18},"file:///f%3A/SocialApp/src/features/posts/useUpdatePost.js":{"language":"JavaScript","code":18,"comment":0,"blank":6},"file:///f%3A/SocialApp/src/features/posts/useUpdateComment.js":{"language":"JavaScript","code":16,"comment":0,"blank":4},"file:///f%3A/SocialApp/src/features/posts/useRepost.js":{"language":"JavaScript","code":25,"comment":2,"blank":8},"file:///f%3A/SocialApp/src/features/posts/usePosts.js":{"language":"JavaScript","code":33,"comment":0,"blank":6},"file:///f%3A/SocialApp/src/features/posts/usePostById.js":{"language":"JavaScript","code":14,"comment":0,"blank":3},"file:///f%3A/SocialApp/src/features/posts/useDeletePost.js":{"language":"JavaScript","code":17,"comment":0,"blank":4},"file:///f%3A/SocialApp/src/features/posts/useLike.js":{"language":"JavaScript","code":21,"comment":3,"blank":7},"file:///f%3A/SocialApp/src/features/posts/useDeleteComment.js":{"language":"JavaScript","code":16,"comment":0,"blank":4},"file:///f%3A/SocialApp/src/features/posts/useCreatePost.js":{"language":"JavaScript","code":17,"comment":0,"blank":4},"file:///f%3A/SocialApp/src/features/posts/useCreateComment.js":{"language":"JavaScript","code":16,"comment":0,"blank":4},"file:///f%3A/SocialApp/src/features/posts/PostFeed.jsx":{"language":"JavaScript JSX","code":72,"comment":1,"blank":16},"file:///f%3A/SocialApp/src/features/posts/useComments.js":{"language":"JavaScript","code":14,"comment":0,"blank":2},"file:///f%3A/SocialApp/src/features/posts/PostCardImage.jsx":{"language":"JavaScript JSX","code":13,"comment":0,"blank":4},"file:///f%3A/SocialApp/src/features/posts/PostCardHeader.jsx":{"language":"JavaScript JSX","code":116,"comment":0,"blank":14},"file:///f%3A/SocialApp/src/features/presence/useUpdateOnlineStatus.js":{"language":"JavaScript","code":26,"comment":5,"blank":7},"file:///f%3A/SocialApp/src/features/posts/PostCardCaption.jsx":{"language":"JavaScript JSX","code":61,"comment":0,"blank":10},"file:///f%3A/SocialApp/src/features/presence/useUserStatus.js":{"language":"JavaScript","code":11,"comment":0,"blank":3},"file:///f%3A/SocialApp/src/features/notifications/useUnreadCount.js":{"language":"JavaScript","code":13,"comment":0,"blank":2},"file:///f%3A/SocialApp/src/features/notifications/useMarkAsRead.js":{"language":"JavaScript","code":17,"comment":0,"blank":4},"file:///f%3A/SocialApp/src/features/notifications/useNotifications.js":{"language":"JavaScript","code":30,"comment":0,"blank":6},"file:///f%3A/SocialApp/src/features/notifications/useMarkAllAsRead.js":{"language":"JavaScript","code":17,"comment":0,"blank":2},"file:///f%3A/SocialApp/src/features/notifications/useDeleteNotification.js":{"language":"JavaScript","code":17,"comment":0,"blank":2},"file:///f%3A/SocialApp/src/features/notifications/useDeleteAllNotifications.js":{"language":"JavaScript","code":17,"comment":0,"blank":2},"file:///f%3A/SocialApp/src/features/notifications/NotificationsList.jsx":{"language":"JavaScript JSX","code":105,"comment":0,"blank":14},"file:///f%3A/SocialApp/src/features/notifications/NotificationTrash.jsx":{"language":"JavaScript JSX","code":4,"comment":0,"blank":2},"file:///f%3A/SocialApp/src/features/notifications/NotificationItem.jsx":{"language":"JavaScript JSX","code":167,"comment":15,"blank":25},"file:///f%3A/SocialApp/package-lock.json":{"language":"JSON","code":3409,"comment":0,"blank":1},"file:///f%3A/SocialApp/src/features/messaging/useMarkMessageAsRead.js":{"language":"JavaScript","code":17,"comment":0,"blank":4},"file:///f%3A/SocialApp/eslint.config.js":{"language":"JavaScript","code":28,"comment":0,"blank":2}}